divexplorer/__init__.py
divexplorer/divexplorer.py
divexplorer/outcomes.py
divexplorer/pattern_processor.py
divexplorer/shapley_value.py
divexplorer/utils_FPgrowth.py
divexplorer/utils_apriori.py
DivExplorer-0.2.6.dist-info/LICENSE
DivExplorer-0.2.6.dist-info/METADATA
DivExplorer-0.2.6.dist-info/WHEEL
DivExplorer-0.2.6.dist-info/top_level.txt
DivExplorer-0.2.6.dist-info/RECORD
