Metadata-Version: 2.1
Name: DivExplorer
Version: 0.2.6
Summary: Analyze Pandas dataframes, and other tabular data (csv), to find subgroups of data with properties that diverge from those of the overall dataset
Author-email: Eliana Pastor <eliana.pastor@polito.it>, Luca de Alfaro <luca@ucsc.edu>
License: MIT License
Project-URL: Homepage, https://divexplorer.github.io/
Project-URL: Source, https://github.com/DivExplorer/divexplorer
Keywords: Pandas,Fairness,Subgroup Analysis,Data Mining
Classifier: Development Status :: 3 - Alpha
Classifier: License :: OSI Approved :: MIT License
Classifier: Programming Language :: Python
Classifier: Programming Language :: Python :: 3
Requires-Python: >=3.7
License-File: LICENSE
Requires-Dist: matplotlib>=3.1.1
Requires-Dist: numpy>=1.16.4
Requires-Dist: mlxtend>=0.17.1
Requires-Dist: pandas>=0.24.2
Requires-Dist: plotly>=4.5.0
Requires-Dist: python_igraph>=0.8.3
